shellper/__init__.py
shellper/datas.py
shellper/inputs.py
shellper/log.py
shellper/style.py
Shellper-0.3.2.4.dist-info/LICENSE.txt
Shellper-0.3.2.4.dist-info/METADATA
Shellper-0.3.2.4.dist-info/WHEEL
Shellper-0.3.2.4.dist-info/top_level.txt
Shellper-0.3.2.4.dist-info/RECORD
