Metadata-Version: 2.1
Name: Shellper
Version: 0.3.2.4
Summary: A Python Library for create shell apps.
Home-page: https://gitee.com/ShawnMerry/Shellper
Author: ShawnMerry
Author-email: merrybili@163.com
Classifier: Development Status :: 4 - Beta
Classifier: Environment :: Console
Classifier: Intended Audience :: Developers
Classifier: Programming Language :: Python :: 3
Classifier: License :: OSI Approved :: Apache Software License
Classifier: Operating System :: OS Independent
Classifier: Topic :: Internet
Requires-Python: >=3.5
License-File: LICENSE.txt
